{
    
    "mine_output":{
        "1":[
            {
                "rate":10,
                "itemid":2000003,
                "count_min":10,
                "count_max":10
            },
            {
                "rate":40,
                "itemid":2000002,
                "count_min":10,
                "count_max":10
            },
            {
                "rate":50,
                "itemid":2000001,
                "count_min":10,
                "count_max":10
            }
        ],
        "2":[
            {
                "rate":10,
                "itemid":101,
                "count_min":10,
                "count_max":10
            },
            {
                "rate":20,
                "itemid":102,
                "count_min":10,
                "count_max":10
            },
            {
                "rate":70,
                "itemid":103,
                "count_min":10,
                "count_max":10
            }
        ]
    }

}